pinfo/__init__.py
ppinfo-0.0.0.dist-info/LICENSE
ppinfo-0.0.0.dist-info/METADATA
ppinfo-0.0.0.dist-info/WHEEL
ppinfo-0.0.0.dist-info/top_level.txt
ppinfo-0.0.0.dist-info/RECORD
