Metadata-Version: 2.1
Name: ppinfo
Version: 0.0.0
Summary: Python Project Info retries information about python projects, such packaging metadata.
License: MIT
Keywords: pypi,packaging
Classifier: Programming Language :: Python :: 3
Requires-Python: >=3.7
License-File: LICENSE
